bobik/__init__.py
bobik/bobik.py
bobikssf-0.3.dist-info/METADATA
bobikssf-0.3.dist-info/WHEEL
bobikssf-0.3.dist-info/top_level.txt
bobikssf-0.3.dist-info/RECORD
